<?xml version="1.0"?>
<!DOCTYPE hibernate-mapping PUBLIC "-//Hibernate/Hibernate Mapping DTD 3.0//EN"
"http://hibernate.sourceforge.net/hibernate-mapping-3.0.dtd">
<!-- Generated Mar 21, 2015 11:35:49 AM by Hibernate Tools 3.4.0.CR1 -->
<hibernate-mapping>
    <class name="com.jotunheim.mimir.domain.Location" table="LOCATION">
        <id name="id" type="long">
            <column name="ID" />
            <generator class="identity" />
        </id>
        <property name="city" type="java.lang.String">
            <column name="CITY" />
        </property>
        <property name="district" type="java.lang.String">
            <column name="DISTRICT" />
        </property>
        <property name="province" type="java.lang.String">
            <column name="PROVINCE" />
        </property>
        <property name="street" type="java.lang.String">
            <column name="STREET" />
        </property>
        <property name="streetNumber" type="java.lang.String">
            <column name="STREETNUMBER" />
        </property>
    </class>
</hibernate-mapping>
